{
  "$id": "1",
  "strings": [
    {
      "Key": "d994a45e-b280-401c-89ee-e482c40905a0",
      "Value": "{g|Military3_1}[Эффекты выбора]{/g} \"Найми в качестве офицеров Владык мечей\"."
    },
    {
      "Key": "d674dd27-0ab1-4641-aa00-8190b1c44f8e",
      "Value": "{g|Military3_2}[Эффекты выбора]{/g} \"Найми в качестве офицеров магов\"."
    },
    {
      "Key": "ec1884b6-3781-4070-afb3-cd9874b7fce4",
      "Value": "\"Я знаю, что ты разбираешься в этом вопросе лучше меня. Реши эту проблему самостоятельно\"."
    },
    {
      "Key": "90b4c9d5-99bc-408d-982c-14946dc19cf4",
      "Value": "\"{mf|Ваша милость|Ваша милость|Ваше величество|Ваше величество}, спешу доложить: набор в армию продолжается, в наших рядах все больше способных солдат. Однако теперь мы столкнулись с кадровой проблемой: нам не хватает офицеров. Искать их среди простых обывателей не стоит: для командования требуются определенные навыки и знания\"."
    },
    {
      "Key": "3ecabf96-b327-40df-bc3e-9995d7f5fb45",
      "Value": "\"Я бы рекомендовал вам набрать офицерский состав из рядов {g|Swordlords}Владык мечей{/g}. Это опытные воины и умелые лидеры, которые обладают тактическим мышлением и способны внушать людям смелость, которая не подведет их на поле боя\"."
    },
    {
      "Key": "ca848280-d823-491d-bd04-a65cafffdf81",
      "Value": "\"Ну что, {name}, опять я. Докладываю: армия растет, солдат все больше. Правда, с командирами у нас затык. Нет способных среди тех, кто просто в солдаты идет. А без командования, сам{mf||а} понимаешь, армией не поуправляешь\"."
    },
    {
      "Key": "adf88a2a-85f7-4034-bb33-b3555866b44a",
      "Value": "\"Кое-где у власти маги или шаманы стоят — они, может, и головастые, только в военном деле ни хрена не смыслят. Зато я, когда в {g|Brevoy}Бревое{/g} была, насмотрелась на этих... Как их... {g|Swordlords}Владык мечей{/g}, да! На вид щуплые, но с оружием управляются как надо и почтением пользуются. Думаю, надо из этих командиров в нашу армию набрать — их точно уважать будут\"."
    },
    {
      "Key": "6669f522-ccff-4c8f-bddb-0e69f7d62fad",
      "Value": "\"Слушай, {name}. Помнишь про набор в войска? В общем, с этим я справился, солдат у нас хоть отбавляй, а вот командовать ими некому\", {n}— Регонгар сплевывает сквозь клыки. — {/n} \"Надо искать кого-то, кого эта бестолочь будет бояться и слушаться. Меня одного на них не хватит\"."
    },
    {
      "Key": "d899a11e-62f5-4577-86ae-3f43536ca241",
      "Value": "\"Знаешь, кого в командиров надо? Не этих придурков из {g|Brevoy}Бревоя{/g}, которые своими ковыряльниками кичатся. Магов! Обычные костоломы против мага никогда не вякнут, если в рожу молнией получить не хотят. И представь только, какой они ужас на поле боя наводить будут — не то что эти {g|Swordlords}Владыки мечей{/g}, которыми {g|Choral}Хорал{/g} пол вытер!\""
    },
    {
      "Key": "d373da7a-33df-449e-8e06-00b519ddbf4a",
      "Value": "{n}Кассиль кивает:{/n} \"Я распоряжусь об этом немедленно\"."
    },
    {
      "Key": "bcc1052d-0665-4ed5-9a85-0fa2c77cfdd2",
      "Value": "{n}Амири довольно хмыкает:{/n} \"Верно. Ладно, пойду доведу твои слова до остальных\"."
    },
    {
      "Key": "7e3793c1-a261-4dbf-ba67-6d9077afcfa6",
      "Value": "{n}Регонгар презрительно хмыкает:{/n} \"Что, и ты туда же? {g|Swordlords}Владыки мечей{/g}, охренеть можно... Да их чернь даже не боится — куда уж солдатам уважать!\""
    },
    {
      "Key": "17f9792d-8a7f-43a2-89c9-a7cf2b30d12c",
      "Value": "\"Но… Откуда заклинателю, просидевшему всю жизнь в своей лаборатории, знать, как вести за собой людей?\" {n}— Кассиль качает головой. —{/n} \"Я… Я думал, что вы поступите иначе\"."
    },
    {
      "Key": "c4cdb0a2-dc42-40cc-8cf5-cc1fdf6f72ea",
      "Value": "{n}Лицо Амири принимает оскорбленный вид:{/n} \"Че-го? Это что, дохляки в робах будут моими орлами командовать? Да ты издеваешься, {name}! Что я с ними делать буду?!\" {n}Амири в сердцах плюет прямо на пол.{/n}"
    },
    {
      "Key": "44b780be-ea28-4197-b9c6-84392d30c620",
      "Value": "\"Отлично! Один-два поджаренных смутьяна — и твои солдаты по струнке ходить будут\"."
    },
    {
      "Key": "6a42ef37-5d3d-4c83-8b6e-aa91a507d773",
      "Value": "\"Благодарю за ваше доверие. Я немедленно отправлю письма тем {g|Swordlords}Владыкам{/g}, которые могут заинтересоваться этим предложением\"."
    },
    {
      "Key": "7eb453db-1de4-438e-adc6-291bf887dc36",
      "Value": "\"Тогда я пойду выясню, как до этих {g|Swordlords}Владык мечей{/g} дозваться. У меня все\"."
    },
    {
      "Key": "1a5b38ca-9ddb-47c9-ac4e-b822bd552fe5",
      "Value": "\"Да знаю я парочку магов, кого во главе отрядов поставить можно. Все устрою\"."
    }
  ]
}