{
  "$id": "1",
  "strings": [
    {
      "Key": "70bd9c06-a6cc-4065-954b-82b29ba440ce",
      "Value": "«Это так. Мы с Регонгаром вместе»."
    },
    {
      "Key": "280e955b-653e-45b2-8fb8-d7f0715908e7",
      "Value": "«Ты прав. Мы с Октавией вместе»."
    },
    {
      "Key": "2cf0f054-2480-4b69-ae00-90c437674e6a",
      "Value": "«Мы просто друзья»."
    },
    {
      "Key": "f437827d-cccd-4670-bdbb-f8797a7b08cb",
      "Value": "«Что это? Ты ревнуешь?»"
    },
    {
      "Key": "89429789-474d-42af-97d3-27ab92af3725",
      "Value": "«Я уже говорила, и не раз: для меня существуешь только ты»."
    },
    {
      "Key": "21f0b3c4-b198-4a60-a1c0-fdf1a9c7f40d",
      "Value": "{n}Тристиан смотрит на вас с напускным безразличием, за которым угадывается тревога:{/n} «Я хотел кое-что узнать, {name}. Если ты не против»."
    },
    {
      "Key": "978482dc-a4c2-45d4-be56-6a9c4820eb83",
      "Value": "«Я видел, как ты общаешься с Регонгаром. Вы… как будто ближе друг другу, чем остальные наши соратники. Вас что-то связывает?»"
    },
    {
      "Key": "2251b6b5-e179-471d-96f0-e3468d9265fe",
      "Value": "«Я видел, как ты веселишься с Октавией. Мне показалось, что между вами существует… нечто особенное. Это так?»"
    },
    {
      "Key": "2b73c685-8afb-4a3d-b46b-4d0c6a0d2f51",
      "Value": "{n}Тристиан выглядит удивлённым.{/n} «Правда? Странно, я подумал… впрочем, неважно. Извини, если я сую нос не в своё дело, {n}— Тристиан с виноватым видом отворачивается, но вдруг бросает на вас быстрый взгляд. —{/n} Надеюсь, ты не единственная, кто так считает»."
    },
    {
      "Key": "8479790a-d59b-4d48-9b53-7baac84d42d2",
      "Value": "«Я… понимаю. Что ж… {n}— Тристиан вздыхает и тепло улыбается. —{/n} Вы замечательная пара. Надеюсь, вас ждёт счастье»."
    },
    {
      "Key": "a775a6d4-d5de-4495-9ce1-759e130aae59",
      "Value": "{n}Тристиан кашляет.{/n} «Я вовсе не… Ох, {name}, умеешь же ты смутить! {n}— жрец неловко смеётся, а потом вдруг становится серьёзным. —{/n} Надеюсь, ты не разобьёшь никому сердце. Впрочем, я уверен, что другие разбираются в отношениях куда лучше, чем я»."
    },
    {
      "Key": "1931c74f-2d14-4cba-8583-158a181eb584",
      "Value": "{n}Тристиан предательски краснеет:{/n} «Нет! О чём ты! Я просто…»"
    }
  ]
}
