{
  "$id": "1",
  "strings": [
    {
      "Key": "cf909a0d-37f8-434a-a1a5-84aeacb8468e",
      "Value": "«Кажись, Тартуччио вообще сюда не за головой Рогача пришёл. Не знаю, что он задумал, но зато знаю, что я сделаю, когда поймаю этого мелкого надутого наглеца…»"
    },
    {
      "Key": "0748c6f6-23e6-4956-bce0-a2a9b2723396",
      "Value": "«Мне тоже показалось, что ему и дела нет до бандитов и их главаря. Что-то тут нечисто…»"
    },
    {
      "Key": "81d17463-be4d-4d1b-a277-ec43c9bf98c8",
      "Value": "«Что бы ни было у него на уме, ему следует помешать»."
    },
    {
      "Key": "f791bef7-b6e4-4635-a910-701374a3d648",
      "Value": "«Этот Тартуччио — скользкий тип. Но такие редко работают сами на себя. Обычно таким нужен кто-то, кто отдаёт приказы…»"
    }
  ]
}
