{
  "$id": "1",
  "strings": [
    {
      "Key": "b9341ddb-85f7-4ef4-9643-931ee8e54037",
      "Value": "«Это просто секс по дружбе!»"
    },
    {
      "Key": "d39f9046-f604-4d0e-8f99-a7b1227ecc69",
      "Value": "«Ты права. Мы очень близки с Октавией»."
    },
    {
      "Key": "31f40081-b2c6-4763-9d2f-c4f6e4a5314f",
      "Value": "«Ты права. Мы очень близки с Регонгаром»."
    },
    {
      "Key": "36414940-32a7-43bb-9658-590e2d7ae1ac",
      "Value": "«В моём сердце нет места ни для кого, кроме тебя»."
    },
    {
      "Key": "d3e6e6d5-c176-4852-a66b-08705e9c1a45",
      "Value": "«{name}? Мне нужно обменяться с тобой парой слов»."
    },
    {
      "Key": "53270260-7cd1-4fbf-91cc-b435c51503c0",
      "Value": "«От меня не укрылось то, что ты поддерживаешь весьма… близкие отношения с кое-кем из своего окружения. Мне это кажется… скажем так, непристойным — учитывая всё то, что ты говорил мне раньше», {n}— Валери смотрит на вас, сложив руки на груди.{/n}"
    },
    {
      "Key": "d516f8e8-dbd9-4425-a520-eef662bbe798",
      "Value": "{n}На лице Валери появляется щучья улыбка:{/n} «О, всего лишь? В таком случае не буду более мешать тебе развлекаться»."
    },
    {
      "Key": "64ed8e4e-8937-45c7-9ce8-0260bed721bc",
      "Value": "{n}Валери задумчиво молчит.{/n} «Жаль, что ты решил уведомить меня об этом только тогда, когда я сама подняла этот вопрос», {n}— Валери отворачивается от вас.{/n}"
    },
    {
      "Key": "f9cb63b8-ab4c-4f6e-9cae-c74a2b723b7c",
      "Value": "{n}Валери склоняет голову набок:{/n} «Ты уверен? Мне кажется, тебе стоило бы прояснить ситуацию с теми, кто… кто близок с тобой. И убедиться, что все правильно друг друга понимают»."
    }
  ]
}
